pyChaining/PyChaining.py
pyChaining/__init__.py
pyChaining-0.0.2.dist-info/LICENSE.txt
pyChaining-0.0.2.dist-info/METADATA
pyChaining-0.0.2.dist-info/WHEEL
pyChaining-0.0.2.dist-info/top_level.txt
pyChaining-0.0.2.dist-info/RECORD
