Metadata-Version: 2.1
Name: pyChaining
Version: 0.0.2
Summary: java stream style(high order, map reduce and method chaining) library for simplify the multiple map and filter operations
Author-email: xethhung <pypi@xethh.dev>
Project-URL: Homepage, https://github.com/xh-dev/pyChaining
Project-URL: Bug Tracker, https://github.com/xh-dev/pyChaining/issues
Classifier: Programming Language :: Python :: 3
Classifier: License :: OSI Approved :: MIT License
Classifier: Operating System :: OS Independent
Requires-Python: >=3.7
License-File: LICENSE.txt
